novapipe/__init__.py
novapipe/cli.py
novapipe/logging_conf.py
novapipe/models.py
novapipe/runner.py
novapipe/tasks.py
novapipe-1.0.0.dist-info/entry_points.txt
novapipe-1.0.0.dist-info/METADATA
novapipe-1.0.0.dist-info/WHEEL
novapipe-1.0.0.dist-info/RECORD
