Metadata-Version: 2.1
Name: novapipe
Version: 1.0.0
Summary: NovaPipe: An advanced, plugin-driven ETL CLI tool
Author: Muqtar Shaikh
Author-email: muqtar.shaikh225@gmail.com
Requires-Python: >=3.8,<4.0
Classifier: Programming Language :: Python :: 3
Classifier: Programming Language :: Python :: 3.8
Classifier: Programming Language :: Python :: 3.9
Classifier: Programming Language :: Python :: 3.10
Classifier: Programming Language :: Python :: 3.11
Classifier: Programming Language :: Python :: 3.12
Classifier: Programming Language :: Python :: 3.13
Requires-Dist: PyYAML (>=6.0,<7.0)
Requires-Dist: click (>=8.1.0,<9.0.0)
Requires-Dist: jinja2 (>=3.1,<4.0)
Requires-Dist: prometheus_client (>=0.16.0,<0.17.0)
Requires-Dist: pydantic (>=2.0,<3.0)
Requires-Dist: rich (>=12.0.0,<13.0.0)
Requires-Dist: tabulate (>=0.9.0,<0.10.0)
